antlr_denter/DenterHelper.py
antlr_denter/__init__.py
antlr_denter-1.3.1.dist-info/METADATA
antlr_denter-1.3.1.dist-info/WHEEL
antlr_denter-1.3.1.dist-info/top_level.txt
antlr_denter-1.3.1.dist-info/RECORD
