Metadata-Version: 2.1
Name: antlr-denter
Version: 1.3.1
Summary: Python-like indentation tokens for ANTLR4
Home-page: https://github.com/yshavit/antlr-denter
Author: yshavit, Bluepuff
License: UNKNOWN
Platform: UNKNOWN
Classifier: Programming Language :: Python :: 3
Classifier: License :: OSI Approved :: MIT License
Classifier: Operating System :: OS Independent
Requires-Python: >=3
